quapp_jupyterlab_s3_bridge/__init__.py
quapp_jupyterlab_s3_bridge/_version.py
quapp_jupyterlab_s3_bridge/app.py
quapp_jupyterlab_s3_bridge/handler.py
quapp_jupyterlab_s3_bridge/manager.py
quapp_jupyterlab_s3_bridge-0.1.0.data/data/share/jupyter/labextensions/quapp-jupyterlab-s3-bridge/build_log.json
quapp_jupyterlab_s3_bridge-0.1.0.data/data/share/jupyter/labextensions/quapp-jupyterlab-s3-bridge/install.json
quapp_jupyterlab_s3_bridge-0.1.0.data/data/share/jupyter/labextensions/quapp-jupyterlab-s3-bridge/package.json
quapp_jupyterlab_s3_bridge-0.1.0.data/data/share/jupyter/labextensions/quapp-jupyterlab-s3-bridge/schemas/quapp-jupyterlab-s3-bridge/package.json.orig
quapp_jupyterlab_s3_bridge-0.1.0.data/data/share/jupyter/labextensions/quapp-jupyterlab-s3-bridge/schemas/quapp-jupyterlab-s3-bridge/plugin.json
quapp_jupyterlab_s3_bridge-0.1.0.data/data/share/jupyter/labextensions/quapp-jupyterlab-s3-bridge/static/lib_index_js.1ef259227089b24bd7d7.js
quapp_jupyterlab_s3_bridge-0.1.0.data/data/share/jupyter/labextensions/quapp-jupyterlab-s3-bridge/static/lib_index_js.1ef259227089b24bd7d7.js.map
quapp_jupyterlab_s3_bridge-0.1.0.data/data/share/jupyter/labextensions/quapp-jupyterlab-s3-bridge/static/remoteEntry.35a2cef62655a50ae03b.js
quapp_jupyterlab_s3_bridge-0.1.0.data/data/share/jupyter/labextensions/quapp-jupyterlab-s3-bridge/static/remoteEntry.35a2cef62655a50ae03b.js.map
quapp_jupyterlab_s3_bridge-0.1.0.data/data/share/jupyter/labextensions/quapp-jupyterlab-s3-bridge/static/style.js
quapp_jupyterlab_s3_bridge-0.1.0.data/data/share/jupyter/labextensions/quapp-jupyterlab-s3-bridge/static/style_index_js.ce9cb11ec554c79f2c10.js
quapp_jupyterlab_s3_bridge-0.1.0.data/data/share/jupyter/labextensions/quapp-jupyterlab-s3-bridge/static/style_index_js.ce9cb11ec554c79f2c10.js.map
quapp_jupyterlab_s3_bridge-0.1.0.data/data/share/jupyter/labextensions/quapp-jupyterlab-s3-bridge/install.json
quapp_jupyterlab_s3_bridge-0.1.0.dist-info/METADATA
quapp_jupyterlab_s3_bridge-0.1.0.dist-info/WHEEL
quapp_jupyterlab_s3_bridge-0.1.0.dist-info/licenses/LICENSE
quapp_jupyterlab_s3_bridge-0.1.0.dist-info/RECORD
